[{"common_name": "Violet-green Swallow", "images": [{"contributor": "Joseph V. Higbee", "src": "http://birdweb.org/birdweb/images/VGSW_jh.jpg", "contributor_url": "http://www.pbase.com/jvhigbee/e_bonw"}, {"contributor": "Tom Grey", "src": "http://birdweb.org/birdweb/images/VGSW_f_tg.jpg", "contributor_url": "http://www.pbase.com/tgrey"}, {"contributor": "Tom Grey", "src": "http://birdweb.org/birdweb/images/VGSW_fl_tg.jpg", "contributor_url": "http://www.pbase.com/tgrey"}], "call": "http://birdweb.org/birdweb/sounds/vgsw1.mp3", "family": "Swallows (Family Hirundinidae)"}, {"common_name": "Northwestern Crow", "images": [{"contributor": "Dennis Paulson", "src": "http://birdweb.org/birdweb/images/nocrdp_x.jpg", "contributor_url": "http://www.pugetsound.edu/academics/academic-resources/slater-museum/"}, {"contributor": "Seattle Audubon", "src": "http://birdweb.org/birdweb/images/nocr2_x.jpg", "contributor_url": "http://seattleaudubon.org/sas/"}], "call": false, "family": "Crows, Jays and Allies (Family Corvidae)"}, {"common_name": "Tree Swallow", "images": [{"contributor": "Tom Grey", "src": "http://birdweb.org/birdweb/images/TRES_tg.jpg", "contributor_url": "http://www.pbase.com/tgrey"}, {"contributor": "Greg Lavaty", "src": "http://birdweb.org/birdweb/images/TRES_fl_gl.jpg", "contributor_url": "http://www.pbase.com/dadas115"}, {"contributor": "Tom Grey", "src": "http://birdweb.org/birdweb/images/TRES_j_tg.jpg", "contributor_url": "http://www.pbase.com/tgrey"}], "call": "http://birdweb.org/birdweb/sounds/TRES01.mp3", "family": "Swallows (Family Hirundinidae)"}, {"common_name": "American Crow", "images": [{"contributor": "Tom Grey", "src": "http://birdweb.org/birdweb/images/AMCR_tg.jpg", "contributor_url": "http://www.pbase.com/tgrey"}, {"contributor": "Greg Lavaty", "src": "http://birdweb.org/birdweb/images/AMCR_fl_gl.jpg", "contributor_url": "http://www.pbase.com/dadas115"}], "call": "http://birdweb.org/birdweb/sounds/amcr1.mp3", "family": "Crows, Jays and Allies (Family Corvidae)"}, {"common_name": "Cliff Swallow", "images": [{"contributor": "Glen Tepke", "src": "http://birdweb.org/birdweb/images/CLSW_fl_gt.jpg", "contributor_url": "http://www.pbase.com/gtepke"}, {"contributor": "Greg Lavaty", "src": "http://birdweb.org/birdweb/images/CLSW_gl.jpg", "contributor_url": "http://www.pbase.com/dadas115"}, {"contributor": "Greg Lavaty", "src": "http://birdweb.org/birdweb/images/CLSW_fl_gl.jpg", "contributor_url": "http://www.pbase.com/dadas115"}, {"contributor": "Tom Grey", "src": "http://birdweb.org/birdweb/images/CLSW_j_tg.jpg", "contributor_url": "http://www.pbase.com/tgrey"}], "call": "http://birdweb.org/birdweb/sounds/clsw1.mp3", "family": "Swallows (Family Hirundinidae)"}, {"common_name": "Black-capped Chickadee", "images": [{"contributor": "Lee Barnes", "src": "http://birdweb.org/birdweb/images/BCCH_lb.jpg", "contributor_url": ""}], "call": "http://birdweb.org/birdweb/sounds/bcch1.mp3", "family": "Chickadees (Family Paridae)"}, {"common_name": "Willow Flycatcher", "images": [{"contributor": "Gregg Thompson", "src": "http://birdweb.org/birdweb/images/WIFL_ad1_gth.jpg", "contributor_url": ""}, {"contributor": "Gregg Thompson", "src": "http://birdweb.org/birdweb/images/WIFL_ad2_gth.jpg", "contributor_url": ""}, {"contributor": "Gregg Thompson", "src": "http://birdweb.org/birdweb/images/WIFL_ad3_gth.jpg", "contributor_url": ""}, {"contributor": "Joseph V. Higbee", "src": "http://birdweb.org/birdweb/images/WIFL_jh.jpg", "contributor_url": "http://www.pbase.com/jvhigbee/e_bonw"}, {"contributor": "Greg Lavaty", "src": "http://birdweb.org/birdweb/images/WIFL_gl.jpg", "contributor_url": "http://www.pbase.com/dadas115"}], "call": "http://birdweb.org/birdweb/sounds/WIFL01.mp3", "family": "Tyrant Flycatchers (Family Tyrannidae)"}, {"common_name": "Warbling Vireo", "images": [{"contributor": "Greg Lavaty", "src": "http://birdweb.org/birdweb/images/wavi_gl.jpg", "contributor_url": "http://www.pbase.com/dadas115"}], "call": "http://birdweb.org/birdweb/sounds/WAVI01.mp3", "family": "Vireos (Family Vireonidae)"}, {"common_name": "Chestnut-backed Chickadee", "images": [{"contributor": "Gregg Thompson", "src": "http://birdweb.org/birdweb/images/CBCH_ad_gth.jpg", "contributor_url": ""}], "call": "http://birdweb.org/birdweb/sounds/cbch2.mp3", "family": "Chickadees (Family Paridae)"}, {"common_name": "Steller's Jay", "images": [{"contributor": "Joseph V. Higbee", "src": "http://birdweb.org/birdweb/images/STJA_jh.jpg", "contributor_url": "http://www.pbase.com/jvhigbee/e_bonw"}], "call": "http://birdweb.org/birdweb/sounds/stja1.mp3", "family": "Crows, Jays and Allies (Family Corvidae)"}, {"common_name": "Barn Swallow", "images": [{"contributor": "Greg Lavaty", "src": "http://birdweb.org/birdweb/images/BARS_f_gl.jpg", "contributor_url": "http://www.pbase.com/dadas115"}, {"contributor": "Greg Lavaty", "src": "http://birdweb.org/birdweb/images/BARS_gl.jpg", "contributor_url": "http://www.pbase.com/dadas115"}, {"contributor": "Glen Tepke", "src": "http://birdweb.org/birdweb/images/BARS_fl_gt.jpg", "contributor_url": "http://www.pbase.com/gtepke"}, {"contributor": "Glen Tepke", "src": "http://birdweb.org/birdweb/images/BARS_j_gt.jpg", "contributor_url": "http://www.pbase.com/gtepke"}], "call": "http://birdweb.org/birdweb/sounds/basw1.mp3", "family": "Swallows (Family Hirundinidae)"}, {"common_name": "Pacific-slope Flycatcher", "images": [{"contributor": "Tom Grey", "src": "http://birdweb.org/birdweb/images/PSFL_tg.jpg", "contributor_url": "http://www.pbase.com/tgrey"}, {"contributor": "Joseph V. Higbee", "src": "http://birdweb.org/birdweb/images/PSFL_jh.jpg", "contributor_url": "http://www.pbase.com/jvhigbee/e_bonw"}], "call": "http://birdweb.org/birdweb/sounds/PSFL01.mp3", "family": "Tyrant Flycatchers (Family Tyrannidae)"}, {"common_name": "Western Scrub-Jay", "images": [{"contributor": "Tom Grey", "src": "http://birdweb.org/birdweb/images/WESJ_tg.jpg", "contributor_url": "http://www.pbase.com/tgrey"}, {"contributor": "Tom Grey", "src": "http://birdweb.org/birdweb/images/WESJ_j_tg.jpg", "contributor_url": "http://www.pbase.com/tgrey"}], "call": false, "family": "Crows, Jays and Allies (Family Corvidae)"}]
